cytosim_reader
