Metadata-Version: 1.0
Name: cytosim-reader
Version: 0.1.0
Summary: Read data from cytosim simulations to numpy arrays.
Home-page: UNKNOWN
Author: Ilyas Kuhlemann
Author-email: ilyasp.ku@gmail.com
License: GNU GPLv3
Platform: UNKNOWN
